CHANGELOG.rst
LICENSE.txt
MANIFEST.in
README.rst
TODO.rst
VERSION.txt
setup.cfg
setup.py
modseclogc/__init__.py
modseclogc/cli.py
modseclogc/engine.py
modseclogc/i18n.py
modseclogc/matcher.py
modseclogc/part.py
modseclogc/record.py
modseclogc/renderer.py
modseclogc/source.py
modseclogc/test_part.py
modseclogc/test_record.py
modseclogc/test_source.py
modseclogc/test_util.py
modseclogc/util.py
modseclogc.egg-info/PKG-INFO
modseclogc.egg-info/SOURCES.txt
modseclogc.egg-info/dependency_links.txt
modseclogc.egg-info/entry_points.txt
modseclogc.egg-info/requires.txt
modseclogc.egg-info/top_level.txt
modseclogc.egg-info/zip-safe