Metadata-Version: 1.1
Name: modseclogc
Version: 0.1.0
Summary: A tool to manipulate and analyze ModSecurity audit log files.
Home-page: http://github.com/metagriffin/modseclogc
Author: metagriffin
Author-email: mg.pypi@uberdev.org
License: GPLv3+
Keywords: modsecurity audit log manipulate analyze command-line library
Platform: any
Classifier: Development Status :: 3 - Alpha
Classifier: Environment :: Console
Classifier: Intended Audience :: Developers
Classifier: Intended Audience :: System Administrators
Classifier: Natural Language :: English
Classifier: Operating System :: OS Independent
Classifier: Programming Language :: Python
Classifier: Topic :: Software Development
Classifier: Topic :: Software Development :: Libraries :: Python Modules
Classifier: Topic :: Utilities
Classifier: License :: OSI Approved :: GNU General Public License v3 or later (GPLv3+)
